{
	"ADS": {
	    
		 "rewarde_type": "aaa",
		"native_type": "aaa",
		"inter_type": "aaa",
		"banner_type": "aaa",
		

        
        
		"unity_id": "",

		"ironsource_id": "",

		"banner_applovin": "5435664",
		"native_applovin": "23435245",
		"interstitial_applovin": "434332245",
		"rewarde_applovin": "244243525",

		"interstitial_admob": "",
		"banner_admob": "",
		"native_admob": "",
		"rewarde_admob": "",

		 
		
		"facebook_interstitial": "",
		"facebook_native": "",
		"facebook_banner": "",
		"facebook_rewarde": ""

		 
	}  
   }
